Numerical_Analysis_Aman/Numerical_Analysis.py
Numerical_Analysis_Aman/__init__.py
numerical_analysis_aman-1.0.0.dist-info/LICENSE
numerical_analysis_aman-1.0.0.dist-info/METADATA
numerical_analysis_aman-1.0.0.dist-info/WHEEL
numerical_analysis_aman-1.0.0.dist-info/top_level.txt
numerical_analysis_aman-1.0.0.dist-info/RECORD
